fsia/__init__.py
fsia/nasagatherer/NasaCredential.py
fsia/nasagatherer/NasaManager.py
fsia/nasagatherer/__init__.py
fsia/tweetgatherer/TweetAnalyzer.py
fsia/tweetgatherer/TweetCriteria.py
fsia/tweetgatherer/TweetManager.py
fsia/tweetgatherer/TweetModel.py
fsia/tweetgatherer/TwitterClient.py
fsia/tweetgatherer/__init__.py
fsia/usgsgatherer/USGSFloodCriteria.py
fsia/usgsgatherer/USGSFloodManager.py
fsia/usgsgatherer/__init__.py
fsia/usgsgatherer/imageProcessor.py
fsia-0.0.3.dist-info/LICENSE
fsia-0.0.3.dist-info/METADATA
fsia-0.0.3.dist-info/WHEEL
fsia-0.0.3.dist-info/top_level.txt
fsia-0.0.3.dist-info/RECORD
