Metadata-Version: 2.1
Name: fsia
Version: 0.0.3
Summary: USGS and Twitter data gathering and analysis tools
Home-page: https://github.com/VidyaSamadi/Research-Team-private
Author: Nattapon Donratanapat
Author-email: pleuk5667@gmail.com
License: UNKNOWN
Platform: UNKNOWN
Classifier: Programming Language :: Python :: 3
Classifier: License :: OSI Approved :: MIT License
Classifier: Operating System :: OS Independent
